MANIFEST.in
README.rst
setup.py
django_blog_it/__init__.py
django_blog_it/settings.py
django_blog_it/test_settings.py
django_blog_it/urls.py
django_blog_it/wsgi.py
django_blog_it.egg-info/PKG-INFO
django_blog_it.egg-info/SOURCES.txt
django_blog_it.egg-info/dependency_links.txt
django_blog_it.egg-info/requires.txt
django_blog_it.egg-info/top_level.txt
django_blog_it/django_blog_it/__init__.py
django_blog_it/django_blog_it/admin.py
django_blog_it/django_blog_it/forms.py
django_blog_it/django_blog_it/mixins.py
django_blog_it/django_blog_it/models.py
django_blog_it/django_blog_it/tests.py
django_blog_it/django_blog_it/urls.py
django_blog_it/django_blog_it/views.py
django_blog_it/django_blog_it/migrations/0001_initial.py
django_blog_it/django_blog_it/migrations/0002_auto_20160223_0521.py
django_blog_it/django_blog_it/migrations/0003_auto_20160224_0410.py
django_blog_it/django_blog_it/migrations/0004_posthistory.py
django_blog_it/django_blog_it/migrations/0005_auto_20160330_0539.py
django_blog_it/django_blog_it/migrations/0006_page.py
django_blog_it/django_blog_it/migrations/0007_menu.py
django_blog_it/django_blog_it/migrations/0008_post_featured_image.py
django_blog_it/django_blog_it/migrations/0009_contactussettings.py
django_blog_it/django_blog_it/migrations/0010_theme.py
django_blog_it/django_blog_it/migrations/0011_auto_20160719_1140.py
django_blog_it/django_blog_it/migrations/0012_auto_20160722_0657.py
django_blog_it/django_blog_it/migrations/0013_facebook.py
django_blog_it/django_blog_it/migrations/0014_post_slugs.py
django_blog_it/django_blog_it/migrations/0015_auto_20180304_1059.py
django_blog_it/django_blog_it/migrations/__init__.py
django_blog_it/django_blog_it/static/ckeditor/galleriffic/js/jquery-1.3.2.js
django_blog_it/django_blog_it/static/css/frontend_main.css
django_blog_it/django_blog_it/static/css/jquery.tagsinput.css
django_blog_it/django_blog_it/static/css/main.css
django_blog_it/django_blog_it/static/css/style.css
django_blog_it/django_blog_it/static/css/menu/dropdown_submenu.css
django_blog_it/django_blog_it/static/css/menu/sm-blue.css
django_blog_it/django_blog_it/static/css/menu/sm-core-css.css
